python_package_cookiecutter_template/__init__.py
python_package_cookiecutter_template/cli.py
python_package_cookiecutter_template/python_package_cookiecutter_template.py
python_package_cookiecutter_template-0.1.1.dist-info/METADATA
python_package_cookiecutter_template-0.1.1.dist-info/RECORD
python_package_cookiecutter_template-0.1.1.dist-info/WHEEL
python_package_cookiecutter_template-0.1.1.dist-info/entry_points.txt
python_package_cookiecutter_template-0.1.1.dist-info/top_level.txt
